{"id":"140455","User_id":"5623263","title":"能动新生领航","type":"活动","intro":"【风华能动】新生领航","logo":"http:\/\/yfs01.fs.yiban.cn\/web\/5623263\/upload\/1505484420352930.jpg","seePrivacy":"全站可见","doPrivacy":"全站用户","layout":"demo","blocks":"{"block1":{"id":"block1","title":"Banner","isDefault":true},"block2":{"id":"block2","title":"嘿，你好新同学","isDefault":true},"block3":{"id":"block3","title":"给小萌新的一封信","isDefault":true},"block4":{"id":"block4","title":"你对专业知多少","visible":true},"block5":{"id":"block5","title":"飒爽军姿你我他","visible":true},"block6":{"id":"block6","title":"我想对你说","visible":true},"block7":{"id":"block7","title":"能动小印记","visible":true},"block8":{"id":"block8","title":"","visible":false},"block9":{"id":"block9","title":"","visible":false},"block10":{"id":"block10","title":"","visible":false}}","widgets":"{"block1":{"0":{"type":"banner","id":"banner-1425994902096","code":"banner","order":1}},"block2":{"0":{"type":"addtext","id":"addtext-1505484453586","code":"addtext-1505484453586","order":1},"1":{"type":"addtext","id":"addtext-1505484535797","code":"addtext-1505484535797","order":2}},"block3":{"0":{"type":"addtext","id":"addtext-1505485708141","code":"addtext-1505485708141","order":1}},"block4":{"0":{"type":"addtext","id":"addtext-1505483171231","code":"addtext-1505483171231","order":1},"1":{"type":"addtext","id":"addtext-1505485999173","code":"addtext-1505485999173","order":2},"2":{"type":"addtext","id":"addtext-1505485995605","code":"addtext-1505485995605","order":3},"3":{"type":"addtext","id":"addtext-1505485989903","code":"addtext-1505485989903","order":4},"4":{"type":"addtext","id":"addtext-1505485993813","code":"addtext-1505485993813","order":5},"5":{"type":"addtext","id":"addtext-1505489062211","code":"addtext-1505489062211","order":6}},"block5":{"0":{"type":"addtext","id":"addtext-1505489907335","code":"addtext-1505489907335","order":1},"1":{"type":"photowall","id":"photowall-1505482302015","code":"photowall-1505482302015","order":2}},"block6":{"0":{"type":"addtext","id":"addtext-1505490397159","code":"addtext-1505490397159","order":1},"1":{"type":"extendcomment","id":"extendcomment-1505557808780","code":"extendcomment-1505557808780","order":2}},"block7":{"0":{"type":"guestbook","id":"guestbook-1505483210109","code":"guestbook","order":1}},"block8":{},"block9":{},"block10":{}}","createTime":"2017-09-15 11:57:03","updateTime":"2018-06-22 00:01:20","checkStatus":"4","status":"2","OpenAppId":"137613","rejectReason":[{"reason":"暂未填写原因","time":"2018-06-17 15:42:10"}],"schoolId":"25009","flag":"0","flower_num":"10","school_name":"兰州理工大学","screen":0}